linux2mqtt/__init__.py
linux2mqtt/__main__.py
linux2mqtt/const.py
linux2mqtt/exceptions.py
linux2mqtt/helpers.py
linux2mqtt/linux2mqtt.py
linux2mqtt/metrics.py
linux2mqtt/package_manager.py
linux2mqtt/py.typed
linux2mqtt/type_definitions.py
linux2mqtt-1.7.0.dist-info/licenses/LICENSE
linux2mqtt-1.7.0.dist-info/METADATA
linux2mqtt-1.7.0.dist-info/WHEEL
linux2mqtt-1.7.0.dist-info/entry_points.txt
linux2mqtt-1.7.0.dist-info/top_level.txt
linux2mqtt-1.7.0.dist-info/RECORD
