Metadata-Version: 2.4
Name: linux2mqtt
Version: 1.7.0
Summary: Send your linux stats and and events to mqtt and discovery them in home assistant.
Author: Adam Cooper
Author-email: Cyrill Raccaud <cyrill.raccaud+pypi@gmail.com>
License: MIT License
Project-URL: Documentation, https://miaucl.github.io/linux2mqtt/
Project-URL: Source, https://github.com/miaucl/linux2mqtt
Project-URL: Issues, https://github.com/miaucl/linux2mqtt/issues
Keywords: linux,mqtt,paho,home-assistant,system-monitoring,discovery,iot
Classifier: Programming Language :: Python :: 3
Classifier: License :: OSI Approved :: MIT License
Classifier: Operating System :: OS Independent
Classifier: Intended Audience :: Information Technology
Classifier: Topic :: System :: Monitoring
Classifier: Topic :: System :: Logging
Classifier: Topic :: System :: Systems Administration
Requires-Python: >=3.11
License-File: LICENSE
Requires-Dist: jsons
Requires-Dist: psutil
Requires-Dist: paho-mqtt
Requires-Dist: typing-extensions
Dynamic: license-file
